<?xml version="1.0" encoding="UTF-8"?>
<!DOCTYPE suite SYSTEM "https://testng.org/testng-1.0.dtd">
<suite name="Suite">
	<groups>
		<run>
			<include name="sanity"></include>
			<include name="master"></include>
			<include name="regression"></include>
		</run>
	</groups>
	<listeners>
		<listener class-name="utilities.extentReport"></listener>
	</listeners>
  <test thread-count="5" name="Test">
    <classes>
      <class name="TestCases.TC_1_UpcomingBikes"/>
      <!--class name="TestCases.TC_3_usedCars"/>
      <class name="TestCases.TC_2_LoginPage"/>-->
    </classes>
  </test> <!-- Test -->
</suite> <!-- Suite -->
